indico_importer_invenio/__init__.py
indico_importer_invenio/connector.py
indico_importer_invenio/converters.py
indico_importer_invenio/forms.py
indico_importer_invenio/importer.py
indico_importer_invenio/plugin.py
indico_importer_invenio/translations/messages.pot
indico_importer_invenio/translations/fr_FR/LC_MESSAGES/messages-js.po
indico_importer_invenio/translations/fr_FR/LC_MESSAGES/messages.mo
indico_importer_invenio/translations/fr_FR/LC_MESSAGES/messages.po
indico_plugin_importer_invenio-2.2.dist-info/METADATA
indico_plugin_importer_invenio-2.2.dist-info/WHEEL
indico_plugin_importer_invenio-2.2.dist-info/entry_points.txt
indico_plugin_importer_invenio-2.2.dist-info/top_level.txt
indico_plugin_importer_invenio-2.2.dist-info/RECORD
